asb_pl_template/__init__.py
asb_pl_template/__main__.py
asb_pl_template/cli.py
asb_pl_template/constants.py
asb_pl_template/core.py
asb_pl_template/lib.py
asb_pl_template/logger.py
tests/__init__.py
tests/test_asb-pl-template.py
asb_pl_template-0.1.5.dist-info/AUTHORS
asb_pl_template-0.1.5.dist-info/METADATA
asb_pl_template-0.1.5.dist-info/WHEEL
asb_pl_template-0.1.5.dist-info/entry_points.txt
asb_pl_template-0.1.5.dist-info/top_level.txt
asb_pl_template-0.1.5.dist-info/RECORD
